statology/__init__.py
statology-0.0.1.dev0.dist-info/LICENSE
statology-0.0.1.dev0.dist-info/METADATA
statology-0.0.1.dev0.dist-info/WHEEL
statology-0.0.1.dev0.dist-info/top_level.txt
statology-0.0.1.dev0.dist-info/RECORD
