Metadata-Version: 2.1
Name: statology
Version: 0.0.1.dev0
Summary: Collection of Statistical Function for Data Science and Analytics
Home-page: https://github.com/sharkutilities/statology
Author: shark-utilities developers
Author-email: statology <neuralNOD@outlook.com>
License: MIT License
Project-URL: Homepage, https://github.com/sharkutilities/statology
Project-URL: Issues, https://github.com/sharkutilities/statology/issues
Project-URL: Changelog, https://github.com/sharkutilities/statology/blob/master/CHANGELOG.md
Keywords: numpy,array,utility,utilities,util,utils,wrappers,data science,data analysis,data scientist,data analyst,statistics,outliers,percentile,quantile,probability
Classifier: Development Status :: 1 - Planning
Classifier: Intended Audience :: Developers
Classifier: Intended Audience :: Education
Classifier: Intended Audience :: End Users/Desktop
Classifier: Intended Audience :: Information Technology
Classifier: Intended Audience :: Science/Research
Classifier: Operating System :: Unix
Classifier: Operating System :: POSIX
Classifier: Operating System :: Microsoft :: Windows
Classifier: Programming Language :: Python
Classifier: Programming Language :: Python :: 3
Classifier: Programming Language :: Python :: 3 :: Only
Classifier: Programming Language :: Python :: 3.9
Classifier: Programming Language :: Python :: 3.10
Classifier: Programming Language :: Python :: 3.11
Classifier: Programming Language :: Python :: 3.12
Classifier: License :: OSI Approved :: MIT License
License-File: LICENSE
